[{"key":"挖掘学术热点-5.提升研究选题精准度4","value":"假设你是[XX领域]专家请对以下选题进行讨论：[选题A]、[选题B]，分析其研究创新性、实践可能性和学术价值。基于讨论结果提出改进方案，并提供可能的优化方向。"},{"key":"挖掘学术热点-5.提升研究选题精准度3","value":"结合以下研究热点：[热点A]、[热点B]，设计深入且具体的研究问题，要求每个问题包含以下内容：1）研究目标的细化；2）关键理论依据；3）支持结论的数据来源。"},{"key":"挖掘学术热点-5.提升研究选题精准度2","value":"列出[领域名称]中3个具体的研究方向，并逐一提供以下分析：1）背景介绍与核心问题；2）当前研究的局限性；3）优化建议，包括研究方法或数据采集策略。"},{"key":"挖掘学术热点-5.提升研究选题精准度1","value":"针对以下研究主题：[主题A]、[主题B]，提出可优化的研究问题，并补充以下内容：1）优化后的研究目标；2）理论创新点；3）可操作的研究方法和数据来源。"},{"key":"挖掘学术热点-4.热点筛选与验证3","value":"对以下研究方向：[方向A]、[方向B]，提出其潜在的研究难点及解决思路，并补充相关案例或成功实践作为参考。"},{"key":"挖掘学术热点-4.热点筛选与验证2","value":"针对以下热点：[热点A]、[热点B]，列出学术价值和实际应用价值最高的研究方向，并补充验证依据（如相关文献或前沿研究现状）。"},{"key":"挖掘学术热点-4.热点筛选与验证1","value":"分析以下研究选题：[选题A]、[选题B]，根据以下标准进行评分：1）学术创新性；2）实践应用性；3）领域相关性；4）数据可得性；5）研究风险。并为每个选题提供改进建议。"},{"key":"挖掘学术热点-3.结合跨学科趋势3","value":"列举[领域A与领域B]交叉领域的3个研究方向，并对每个方向提供详细的理论背景、数据需求和学术空白分析。"},{"key":"挖掘学术热点-3.结合跨学科趋势2","value":"设计关于[学科A与学科B]结合的学术研究方向，提供以下信息：1）选题的学术贡献；2）跨学科协作的可能性；3）实际应用场景及潜在社会影响。"},{"key":"挖掘学术热点-3.结合跨学科趋势1","value":"从[学科A]与[学科B]结合的视角，生成3个跨学科的研究热点。为每个热点补充以下内容：1）跨学科协作的可能性；2）理论框架的整合思路；3）可能的研究方法与实际应用场景。"},{"key":"挖掘学术热点-2.分析已有热点并拓展新领域3","value":"对以下研究热点：[热点A]、[热点B]，提出可结合的交叉研究方向，具体阐述每个方向的理论依据、可能的学术空白和实际挑战。"},{"key":"挖掘学术热点-2.分析已有热点并拓展新领域2","value":"结合[热点名称]的当前研究进展，分析其理论缺口与学术空白，生成创新性选题，并补充具体操作方案，包括数据采集方式与可能的模型框架。"},{"key":"挖掘学术热点-2.分析已有热点并拓展新领域1","value":"基于以下热点：[热点A]、[热点B]、[热点C]，设计3个创新性研究方向。每个方向需包含：1）对现有热点的理论缺口分析；2）潜在研究目标；3）预期的研究方法与数据需求。"},{"key":"挖掘学术热点-1.明确研究领域和方向3","value":"针对[领域名称]，提出5个具体研究选题。每个选题需包括以下信息：1）研究背景与意义；2）选题的创新性；3）关键数据来源及研究可行性评估。"},{"key":"挖掘学术热点-1.明确研究领域和方向2","value":"列出[具体学科/方向]中3-5个当前备受关注的研究热点，并对每个热点提供以下内容：1）相关的代表性文献或理论模型；2）学术发展趋势；3）该热点的研究难点与未来可能的研究方向。"},{"key":"挖掘学术热点-1.明确研究领域和方向1","value":"总结近五年（20XX-20XX）[领域名称]领域的主要研究热点，按理论型研究和实验型研究分类，并对每个热点进行以下分析：1）理论基础与核心概念；2）当前研究状态和关键问题；3）潜在学术价值与实际应用。"}]